LICENSE
MANIFEST.in
README.md
pytest_gitlabci_parallelized.py
setup.py
pytest_gitlabci_parallelized.egg-info/PKG-INFO
pytest_gitlabci_parallelized.egg-info/SOURCES.txt
pytest_gitlabci_parallelized.egg-info/dependency_links.txt
pytest_gitlabci_parallelized.egg-info/entry_points.txt
pytest_gitlabci_parallelized.egg-info/requires.txt
pytest_gitlabci_parallelized.egg-info/top_level.txt