Metadata-Version: 2.1
Name: pytest-gitlabci-parallelized
Version: 0.1.3
Summary: Parallelize pytest across GitLab CI workers.
Home-page: https://github.com/mlesniew/pytest-gitlabci-parallelized
Author: Michał Leśniewski, Ryan Wilson-Perkin
Author-email: mlesniew@gmail.com
License: MIT
Platform: UNKNOWN
Classifier: Framework :: Pytest
Classifier: Intended Audience :: Developers
Classifier: Topic :: Software Development :: Testing
Classifier: Programming Language :: Python
Classifier: Programming Language :: Python :: 2
Classifier: Programming Language :: Python :: 2.7
Classifier: Programming Language :: Python :: 3
Classifier: Programming Language :: Python :: 3.4
Classifier: Programming Language :: Python :: 3.5
Classifier: Programming Language :: Python :: 3.6
Classifier: Programming Language :: Python :: 3.7
Classifier: Operating System :: OS Independent
Classifier: License :: OSI Approved :: MIT License
Requires-Python: >=2.7, !=3.0.*, !=3.1.*, !=3.2.*, !=3.3.*
License-File: LICENSE
